darklab/__init__.py
darklab/cipher.py
darklab/mee6.py
darklab/utils.py
darklab-0.1.1.dist-info/LICENSE
darklab-0.1.1.dist-info/METADATA
darklab-0.1.1.dist-info/WHEEL
darklab-0.1.1.dist-info/top_level.txt
darklab-0.1.1.dist-info/RECORD
