Metadata-Version: 2.1
Name: darklab
Version: 0.1.1
Summary: DarkCeptor44's utility package
Home-page: UNKNOWN
Author: DarkCeptor44
Author-email: murilomp44@gmail.com
License: UNKNOWN
Platform: UNKNOWN
Classifier: Programming Language :: Python :: 3
Classifier: License :: OSI Approved :: MIT License
Classifier: Operating System :: OS Independent
Requires-Python: >=3.6
